ruamel/yaml/__init__.py
ruamel/yaml/anchor.py
ruamel/yaml/comments.py
ruamel/yaml/compat.py
ruamel/yaml/composer.py
ruamel/yaml/configobjwalker.py
ruamel/yaml/constructor.py
ruamel/yaml/cyaml.py
ruamel/yaml/docinfo.py
ruamel/yaml/dumper.py
ruamel/yaml/emitter.py
ruamel/yaml/error.py
ruamel/yaml/events.py
ruamel/yaml/loader.py
ruamel/yaml/main.py
ruamel/yaml/mergevalue.py
ruamel/yaml/nodes.py
ruamel/yaml/parser.py
ruamel/yaml/py.typed
ruamel/yaml/reader.py
ruamel/yaml/representer.py
ruamel/yaml/resolver.py
ruamel/yaml/scalarbool.py
ruamel/yaml/scalarfloat.py
ruamel/yaml/scalarint.py
ruamel/yaml/scalarstring.py
ruamel/yaml/scanner.py
ruamel/yaml/serializer.py
ruamel/yaml/tag.py
ruamel/yaml/timestamp.py
ruamel/yaml/tokens.py
ruamel/yaml/util.py
ruamel/yaml/clibz/__init__.py
ruamel/yaml/clibz/setup.py
ruamel_yaml-0.19.0.dist-info/licenses/LICENSE
ruamel_yaml-0.19.0.dist-info/METADATA
ruamel_yaml-0.19.0.dist-info/WHEEL
ruamel_yaml-0.19.0.dist-info/top_level.txt
ruamel_yaml-0.19.0.dist-info/RECORD
